Metadata-Version: 1.0
Name: savvidistributions
Version: 0.1
Summary: Gaussian distributions and Binomial distributions
Home-page: UNKNOWN
Author: Olatunde Babawale
Author-email: obabawale@pm.me
License: UNKNOWN
Platform: UNKNOWN
